investimentos/__init__.py
investimentos/investimentos.py
investpy_mptrivelato-1.0.0.dist-info/METADATA
investpy_mptrivelato-1.0.0.dist-info/WHEEL
investpy_mptrivelato-1.0.0.dist-info/top_level.txt
investpy_mptrivelato-1.0.0.dist-info/RECORD
