Metadata-Version: 2.1
Name: investpy-mptrivelato
Version: 1.0.0
Summary: Biblioteca com funções de calculos de investimento,
Home-page: https://github.com/marcostrivelato/Hands-on/investpy
Author: MpTrivelato
Author-email: mp.trivelato@gmail.com 
License: MIT
Platform: UNKNOWN
